iotbotocredentialprovider/AWS.py
iotbotocredentialprovider/FakeMetadata.py
iotbotocredentialprovider/__init__.py
iotbotocredentialprovider-1.0.1.data/scripts/fakemetadata-server.py
iotbotocredentialprovider-1.0.1.dist-info/DESCRIPTION.rst
iotbotocredentialprovider-1.0.1.dist-info/METADATA
iotbotocredentialprovider-1.0.1.dist-info/RECORD
iotbotocredentialprovider-1.0.1.dist-info/WHEEL
iotbotocredentialprovider-1.0.1.dist-info/metadata.json
iotbotocredentialprovider-1.0.1.dist-info/top_level.txt
