Metadata-Version: 2.0
Name: iotbotocredentialprovider
Version: 1.0.1
Summary: AWS IoT Credential Provider: create boto sessions which obtain and renew credentials from an AWS IoT device certificate
Home-page: https://github.com/craighagan/iotbotocredentialprovider
Author: Craig I. Hagan
Author-email: hagan@cih.com
License: MIT
Platform: UNKNOWN
Requires-Dist: boto3
Requires-Dist: requests
